cdst/__init__.py
cdst/cli.py
cdst/core.py
cdst_genome-0.2.1.dist-info/licenses/LICENSE
cdst_genome-0.2.1.dist-info/METADATA
cdst_genome-0.2.1.dist-info/WHEEL
cdst_genome-0.2.1.dist-info/entry_points.txt
cdst_genome-0.2.1.dist-info/top_level.txt
cdst_genome-0.2.1.dist-info/RECORD
