Metadata-Version: 2.4
Name: cdst-genome
Version: 0.2.1
Summary: CoDing Sequence Typer (CDST): MD5 hash-based genome typing and clustering
Author: Collaborators
Author-email: Menghan Li <your_email@example.com>
License: GPL-3.0-only
Project-URL: Homepage, https://github.com/l1-mh/CDST
Project-URL: Issues, https://github.com/l1-mh/CDST/issues
Project-URL: Documentation, https://github.com/l1-mh/CDST#readme
Classifier: Programming Language :: Python :: 3
Classifier: License :: OSI Approved :: GNU General Public License v3 (GPLv3)
Classifier: Operating System :: OS Independent
Classifier: Intended Audience :: Science/Research
Classifier: Topic :: Scientific/Engineering :: Bio-Informatics
Requires-Python: >=3.9
License-File: LICENSE
Requires-Dist: biopython>=1.85
Requires-Dist: pandas>=2.2
Requires-Dist: networkx>=3.3
Requires-Dist: scipy>=1.13
Dynamic: license-file
